netbox_multicast_stream_mapping/__init__.py
netbox_multicast_stream_mapping/filtersets.py
netbox_multicast_stream_mapping/forms.py
netbox_multicast_stream_mapping/models.py
netbox_multicast_stream_mapping/navigation.py
netbox_multicast_stream_mapping/search.py
netbox_multicast_stream_mapping/tables.py
netbox_multicast_stream_mapping/urls.py
netbox_multicast_stream_mapping/views.py
netbox_multicast_stream_mapping/api/__init__.py
netbox_multicast_stream_mapping/api/serializers.py
netbox_multicast_stream_mapping/api/urls.py
netbox_multicast_stream_mapping/api/views.py
netbox_multicast_stream_mapping/migrations/0001_initial.py
netbox_multicast_stream_mapping/migrations/0002_remove_processor_default_action_and_more.py
netbox_multicast_stream_mapping/migrations/0003_alter_processor_device_alter_processor_module.py
netbox_multicast_stream_mapping/migrations/0004_multicastsender.py
netbox_multicast_stream_mapping/migrations/0005_rename_multicastsender_sender.py
netbox_multicast_stream_mapping/migrations/0006_receiver.py
netbox_multicast_stream_mapping/migrations/0007_receiver_switch_method_stream.py
netbox_multicast_stream_mapping/migrations/0008_rename_bandwith_stream_bandwidth_and_more.py
netbox_multicast_stream_mapping/migrations/0009_remove_receiver_max_bandwith_in_and_more.py
netbox_multicast_stream_mapping/migrations/0010_alter_sender_processor.py
netbox_multicast_stream_mapping/migrations/0011_alter_processor_comments_alter_processor_description_and_more.py
netbox_multicast_stream_mapping/migrations/0012_alter_receiver_processor.py
netbox_multicast_stream_mapping/migrations/0013_alter_processor_device.py
netbox_multicast_stream_mapping/migrations/0014_alter_processor_module.py
netbox_multicast_stream_mapping/migrations/0015_remove_receiver_receiver_port_and_more.py
netbox_multicast_stream_mapping/migrations/0016_alter_sender_signal_type.py
netbox_multicast_stream_mapping/migrations/0017_alter_receiver_receiver_ip_and_more.py
netbox_multicast_stream_mapping-0.3.dist-info/METADATA
netbox_multicast_stream_mapping-0.3.dist-info/WHEEL
netbox_multicast_stream_mapping-0.3.dist-info/top_level.txt
netbox_multicast_stream_mapping-0.3.dist-info/RECORD
