Metadata-Version: 2.1
Name: netbox-multicast-stream-mapping
Version: 0.3
Summary: A Plugin to map multicast streams to netbox devices
